odoo/addons/l10n_it_corrispettivi_fatturapa_out/README.rst
odoo/addons/l10n_it_corrispettivi_fatturapa_out/__init__.py
odoo/addons/l10n_it_corrispettivi_fatturapa_out/__manifest__.py
odoo/addons/l10n_it_corrispettivi_fatturapa_out/i18n/it.po
odoo/addons/l10n_it_corrispettivi_fatturapa_out/i18n/l10n_it_corrispettivi_fatturapa_out.pot
odoo/addons/l10n_it_corrispettivi_fatturapa_out/readme/DESCRIPTION.rst
odoo/addons/l10n_it_corrispettivi_fatturapa_out/static/description/icon.png
odoo/addons/l10n_it_corrispettivi_fatturapa_out/static/description/index.html
odoo/addons/l10n_it_corrispettivi_fatturapa_out/views/account_invoice_view.xml
odoo12_addon_l10n_it_corrispettivi_fatturapa_out-12.0.1.0.1.dist-info/METADATA
odoo12_addon_l10n_it_corrispettivi_fatturapa_out-12.0.1.0.1.dist-info/WHEEL
odoo12_addon_l10n_it_corrispettivi_fatturapa_out-12.0.1.0.1.dist-info/top_level.txt
odoo12_addon_l10n_it_corrispettivi_fatturapa_out-12.0.1.0.1.dist-info/RECORD
