Metadata-Version: 2.1
Name: odoo12-addon-l10n-it-corrispettivi-fatturapa-out
Version: 12.0.1.0.1
Summary: Modulo per integrare ricevute e fatturazione elettronica
Home-page: https://github.com/OCA/l10n-italy/tree/12.0/l10n_it_corrispettivi_fatturapa_out
Author: Odoo Community Association (OCA)
Author-email: support@odoo-community.org
License: AGPL-3
Platform: UNKNOWN
Classifier: Programming Language :: Python
Classifier: Framework :: Odoo
Classifier: License :: OSI Approved :: GNU Affero General Public License v3
Requires-Python: >=3.5
Requires-Dist: odoo12-addon-l10n-it-corrispettivi
Requires-Dist: odoo12-addon-l10n-it-fatturapa-out
Requires-Dist: odoo (<12.1dev,>=12.0a)
